hf_trainer_nbconvert/__init__.py
hf_trainer_nbconvert/cli.py
hf_trainer_nbconvert/converter.py
hf_trainer_nbconvert/enhanced_converter.py
hf_trainer_nbconvert-1.0.1.dist-info/licenses/LICENSE
hf_trainer_nbconvert-1.0.1.dist-info/METADATA
hf_trainer_nbconvert-1.0.1.dist-info/WHEEL
hf_trainer_nbconvert-1.0.1.dist-info/entry_points.txt
hf_trainer_nbconvert-1.0.1.dist-info/top_level.txt
hf_trainer_nbconvert-1.0.1.dist-info/RECORD
