Metadata-Version: 2.4
Name: hf-trainer-nbconvert
Version: 1.0.1
Summary: Convert HuggingFace Trainer notebooks to HTML with preserved training data
Home-page: https://github.com/yourusername/hf-trainer-nbconvert
Author: K N S Sri Harshith
Author-email: K N S Sri Harshith <knssriharshith@gmail.com>
License: MIT
Project-URL: Homepage, https://github.com/yourusername/hf-trainer-nbconvert
Project-URL: Documentation, https://github.com/yourusername/hf-trainer-nbconvert#readme
Project-URL: Repository, https://github.com/yourusername/hf-trainer-nbconvert
Project-URL: Bug Reports, https://github.com/yourusername/hf-trainer-nbconvert/issues
Keywords: jupyter,notebook,huggingface,trainer,machine-learning,html,conversion,nbconvert,ml,ai
Classifier: Development Status :: 5 - Production/Stable
Classifier: Intended Audience :: Developers
Classifier: Intended Audience :: Science/Research
Classifier: License :: OSI Approved :: MIT License
Classifier: Operating System :: OS Independent
Classifier: Programming Language :: Python :: 3
Classifier: Programming Language :: Python :: 3.8
Classifier: Programming Language :: Python :: 3.9
Classifier: Programming Language :: Python :: 3.10
Classifier: Programming Language :: Python :: 3.11
Classifier: Programming Language :: Python :: 3.12
Classifier: Topic :: Scientific/Engineering :: Artificial Intelligence
Classifier: Topic :: Software Development :: Libraries :: Python Modules
Classifier: Topic :: Text Processing :: Markup :: HTML
Requires-Python: >=3.8
License-File: LICENSE
Requires-Dist: nbformat>=5.7.0
Requires-Dist: nbconvert>=7.0.0
Requires-Dist: matplotlib>=3.5.0
Requires-Dist: numpy>=1.21.0
Requires-Dist: transformers>=4.20.0
Requires-Dist: jupyter>=1.0.0
Dynamic: author
Dynamic: home-page
Dynamic: license-file
Dynamic: requires-python
